Metadata-Version: 1.2
Name: django-jsonfield
Version: 1.4.0
Summary: JSONField for django models
Home-page: https://github.com/adamchainz/django-jsonfield
Author: Matthew Schinckel
Author-email: matt@schinckel.net
Maintainer: Adam Johnson
Maintainer-email: me@adamj.eu
License: UNKNOWN
Platform: UNKNOWN
Classifier: Development Status :: 6 - Mature
Classifier: Framework :: Django
Classifier: Framework :: Django :: 1.11
Classifier: Framework :: Django :: 2.0
Classifier: Framework :: Django :: 2.1
Classifier: Framework :: Django :: 2.2
Classifier: Intended Audience :: Developers
Classifier: License :: OSI Approved :: BSD License
Classifier: Operating System :: OS Independent
Classifier: Programming Language :: Python
Classifier: Programming Language :: Python :: 2
Classifier: Programming Language :: Python :: 3
